reflectivipy/__init__.py
reflectivipy/core.py
reflectivipy/reflectivity.py
reflectivipy/reifications.py
reflectivipy/wrappers/__init__.py
reflectivipy/wrappers/assign_flatwrapper.py
reflectivipy/wrappers/call_flatwrapper.py
reflectivipy/wrappers/cflow_flatwrapper.py
reflectivipy/wrappers/compare_flatwrapper.py
reflectivipy/wrappers/expr_flatwrapper.py
reflectivipy/wrappers/flatwrapper.py
reflectivipy/wrappers/literal_flatwrapper.py
reflectivipy/wrappers/method_flatwrapper.py
reflectivipy/wrappers/return_flatwrapper.py
reflectivipy-0.1.1.dist-info/LICENSE
reflectivipy-0.1.1.dist-info/METADATA
reflectivipy-0.1.1.dist-info/WHEEL
reflectivipy-0.1.1.dist-info/top_level.txt
reflectivipy-0.1.1.dist-info/RECORD
