Metadata-Version: 2.1
Name: reflectivipy
Version: 0.1.1
Summary: A Python Implementation of the Reflectivity API from the Pharo language
Home-page: https://github.com/StevenCostiou/reflectivipy
Author: Steven Costiou
Author-email: steven.costiou@abc.fr
License: UNKNOWN
Keywords: object-centric partial-behavior-reflection metaprogramming
Platform: UNKNOWN
Classifier: Development Status :: 3 - Alpha
Classifier: Programming Language :: Python
Classifier: Programming Language :: Python :: 3
Classifier: Programming Language :: Python :: Implementation :: PyPy
Classifier: Programming Language :: Python :: Implementation :: CPython
Classifier: Operating System :: OS Independent
Classifier: Intended Audience :: Developers
Classifier: Topic :: Software Development
Classifier: Topic :: Software Development :: Libraries
Classifier: Topic :: Software Development :: Code Generators
Classifier: Topic :: Software Development :: Debuggers
